sms/__init__.py
sms/message.py
sms/signals.py
sms/utils.py
sms/backends/__init__.py
sms/backends/aws_backend.py
sms/backends/base.py
sms/backends/console_backend.py
sms/backends/dummy_backend.py
sms/backends/file_backend.py
sms/backends/locmem_backend.py
sms/backends/messagebird_backend.py
sms/backends/twilio_backend.py
tests/__init__.py
tests/custombackend.py
tests/runtests.py
tests/tests.py
care_sms-1.0.0.dist-info/LICENSE
care_sms-1.0.0.dist-info/METADATA
care_sms-1.0.0.dist-info/WHEEL
care_sms-1.0.0.dist-info/top_level.txt
care_sms-1.0.0.dist-info/RECORD
