Metadata-Version: 2.1
Name: care-sms
Version: 1.0.0
Summary: A Django package for sending SMS using multiple backends.
Home-page: https://github.com/DraKen0009/care-sms
Author: Prafful Sharma
Author-email: praffulsharma1230@gmail.com
License: MIT
Classifier: Programming Language :: Python :: 3
Classifier: Framework :: Django
Classifier: License :: OSI Approved :: MIT License
Classifier: Operating System :: OS Independent
Requires-Python: >=3.8
License-File: LICENSE
Requires-Dist: django >=3.2
Provides-Extra: all
Requires-Dist: boto3 >=1.17.0 ; extra == 'all'
Requires-Dist: messagebird >=1.5.0 ; extra == 'all'
Requires-Dist: twilio >=7.0.0 ; extra == 'all'
Provides-Extra: boto3
Requires-Dist: boto3 >=1.17.0 ; extra == 'boto3'
Provides-Extra: messagebird
Requires-Dist: messagebird >=1.5.0 ; extra == 'messagebird'
Provides-Extra: twilio
Requires-Dist: twilio >=7.0.0 ; extra == 'twilio'
